dropblock/__init__.py
dropblock/dropblock.py
dropblock/scheduler.py
dropblock-0.3.0.dist-info/LICENSE
dropblock-0.3.0.dist-info/METADATA
dropblock-0.3.0.dist-info/WHEEL
dropblock-0.3.0.dist-info/top_level.txt
dropblock-0.3.0.dist-info/RECORD
